md2zhihu/__init__.py
md2zhihu/__main__.py
md2zhihu/make-action-doc.py
md2zhihu/setup.py
md2zhihu/version.py
md2zhihu/md2zhihu/__init__.py
md2zhihu/mistune/__init__.py
md2zhihu/mistune/block_parser.py
md2zhihu/mistune/inline_parser.py
md2zhihu/mistune/markdown.py
md2zhihu/mistune/renderers.py
md2zhihu/mistune/scanner.py
md2zhihu/mistune/plugins/__init__.py
md2zhihu/mistune/plugins/def_list.py
md2zhihu/mistune/plugins/extra.py
md2zhihu/mistune/plugins/footnotes.py
md2zhihu/mistune/plugins/table.py
md2zhihu/mistune/plugins/task_lists.py
md2zhihu-0.14.dist-info/METADATA
md2zhihu-0.14.dist-info/WHEEL
md2zhihu-0.14.dist-info/entry_points.txt
md2zhihu-0.14.dist-info/top_level.txt
md2zhihu-0.14.dist-info/RECORD
