Metadata-Version: 2.1
Name: md2zhihu
Version: 0.14
Summary: convert markdown to zhihu compatible format. https://github.com/drmingdrmer/md2zhihu
Home-page: https://github.com/drmingdrmer/md2zhihu
Author: Zhang Yanpo
Author-email: drdr.xp@gmail.com
License: MIT
Keywords: python,markdown,zhihu
Platform: UNKNOWN
Classifier: Development Status :: 4 - Beta
Classifier: Intended Audience :: Developers
Classifier: Topic :: Software Development :: Libraries
Classifier: Programming Language :: Python :: 3
Requires-Python: >=3.0
Requires-Dist: PyYAML (>=5.3.1)
Requires-Dist: k3color (>=0.1.2)
Requires-Dist: k3down2 (>=0.1.15)
Requires-Dist: k3fs (>=0.1.5)
Requires-Dist: k3git (>=0.1.6)
Requires-Dist: k3handy (>=0.1.5)
